Metadata-Version: 1.0
Name: bin-gaus-dist
Version: 1.1
Summary: Binomial Gaussian distributions
Home-page: UNKNOWN
Author: Avirup Mondal
Author-email: xyz@example.com
License: UNKNOWN
Platform: UNKNOWN
